syncontrol/__init__.py
syncontrol/causal_impact.py
syncontrol-0.2.dist-info/METADATA
syncontrol-0.2.dist-info/WHEEL
syncontrol-0.2.dist-info/top_level.txt
syncontrol-0.2.dist-info/RECORD
